mcp_novelaigen/__init__.py
mcp_novelaigen/server.py
mcp_novelaigen-0.2.21.dist-info/METADATA
mcp_novelaigen-0.2.21.dist-info/WHEEL
mcp_novelaigen-0.2.21.dist-info/entry_points.txt
mcp_novelaigen-0.2.21.dist-info/licenses/LICENSE
mcp_novelaigen-0.2.21.dist-info/RECORD
