Metadata-Version: 2.4
Name: mcp-novelaigen
Version: 0.2.21
Summary: A NovelAI image generation tool as an MCP server
Author: Kilo Code
License-File: LICENSE
Classifier: License :: OSI Approved :: MIT License
Classifier: Operating System :: OS Independent
Classifier: Programming Language :: Python :: 3
Requires-Python: >=3.10
Requires-Dist: aiohttp
Requires-Dist: fastapi
Requires-Dist: mcp>=1.0.0
Requires-Dist: pillow
Requires-Dist: uvicorn
Provides-Extra: test
Requires-Dist: aiohttp; extra == 'test'
Requires-Dist: pytest; extra == 'test'
Requires-Dist: pytest-asyncio; extra == 'test'
